leda/__init__.py
leda/__main__.py
leda/py.typed
leda/version.py
leda/gen/__init__.py
leda/gen/base.py
leda/gen/generators.py
leda/gen/html_utils.py
leda/gen/modifiers.py
leda/gen/publishers.py
leda/gen/runners.py
leda/interacting/__init__.py
leda/interacting/base.py
leda/interacting/core.py
leda/interacting/dynamic.py
leda/interacting/func_gen.py
leda/interacting/helpers.py
leda/interacting/magics.py
leda/interacting/panel.py
leda/interacting/params.py
leda/interacting/static_ipywidgets.py
leda/templates/__init__.py
leda/templates/lab_narrow/__init__.py
leda/templates/lab_narrow/conf.json
leda/templates/lab_narrow/index.html.j2
leda/tests/__init__.py
leda/tests/test_interact_func_gen.py
leda/tests/integration/__init__.py
leda/tests/integration/run_test.py
leda/tests/integration/run_tests.py
leda/vendor/__init__.py
leda/vendor/static_ipywidgets/.gitignore
leda/vendor/static_ipywidgets/LICENSE
leda/vendor/static_ipywidgets/README.md
leda/vendor/static_ipywidgets/TODO.md
leda/vendor/static_ipywidgets/__init__.py
leda/vendor/static_ipywidgets/setup.py.disable
leda/vendor/static_ipywidgets/static_ipywidgets/__init__.py
leda/vendor/static_ipywidgets/static_ipywidgets/interact.py
leda/vendor/static_ipywidgets/static_ipywidgets/plotly_figure.tpl
leda/vendor/static_ipywidgets/static_ipywidgets/static_plotly_utils.py
leda/vendor/static_ipywidgets/static_ipywidgets/widgets.py
leda/vendor/static_ipywidgets/static_ipywidgets/tests/test_interact.py
leda-1.0.0.dist-info/METADATA
leda-1.0.0.dist-info/WHEEL
leda-1.0.0.dist-info/licenses/LICENSE
leda-1.0.0.dist-info/RECORD
