Metadata-Version: 2.4
Name: leda
Version: 1.0.0
Summary: Generate static reports from Jupyter notebooks
Project-URL: Homepage, https://github.com/ansatzcapital/leda
Project-URL: Packaging, https://pypi.org/project/leda
Project-URL: Source, https://github.com/ansatzcapital/leda
Project-URL: Tracker, https://github.com/ansatzcapital/leda/issues
License:                                  Apache License
License-File: LICENSE
Keywords: Jupyter,data,notebooks,reports,visualization
Classifier: Development Status :: 5 - Production/Stable
Classifier: Framework :: Jupyter
Classifier: Framework :: Matplotlib
Classifier: Intended Audience :: Developers
Classifier: Operating System :: OS Independent
Classifier: Programming Language :: Python :: 3.8
Classifier: Programming Language :: Python :: 3.9
Classifier: Programming Language :: Python :: 3.10
Classifier: Programming Language :: Python :: 3.11
Classifier: Programming Language :: Python :: 3.12
Classifier: Programming Language :: Python :: 3.13
Classifier: Programming Language :: Python :: 3.14
Classifier: Programming Language :: Python :: Implementation :: CPython
Classifier: Programming Language :: Python :: Implementation :: PyPy
Classifier: Topic :: Scientific/Engineering :: Visualization
Classifier: Topic :: Software Development :: Libraries
Requires-Python: >=3.8
Requires-Dist: ipython>=7.16.1
Requires-Dist: ipywidgets>=7.5.1
Requires-Dist: markdown2>=2.3.9
Requires-Dist: matplotlib>=2.2.5
Requires-Dist: nbconvert>=5.6.1
Requires-Dist: nbformat>=5.0.4
Requires-Dist: packaging>=19.0.0
Requires-Dist: plotly>=4.6.0
Requires-Dist: termcolor>=1.1.0
Requires-Dist: tqdm>=4.48.2
Requires-Dist: typing-extensions>=4.4.0
Provides-Extra: panel
Requires-Dist: panel>=0.14.1; extra == 'panel'
